afas_connector/__init__.py
afas_connector/afas_connector.py
afas_connector/afas_filter.py
afas_connector/afas_object.py
afas_connector-0.1.5.dist-info/LICENSE
afas_connector-0.1.5.dist-info/METADATA
afas_connector-0.1.5.dist-info/WHEEL
afas_connector-0.1.5.dist-info/top_level.txt
afas_connector-0.1.5.dist-info/RECORD
