Metadata-Version: 2.1
Name: afas_connector
Version: 0.1.5
Summary: AfasConnector is a Python package that simplifies interacting with AFAS Connectors via HTTP requests. It provides classes for making GET, POST, and PUT requests to AFAS Connectors and handling their responses.
Home-page: https://github.com/bakeable/afas-connector
Author: Robin Bakker
Author-email: robin@bakeable.nl
License: MIT
Classifier: Programming Language :: Python :: 3
Classifier: License :: OSI Approved :: MIT License
Classifier: Operating System :: OS Independent
Requires-Python: >=3.12
License-File: LICENSE
Requires-Dist: requests >=2.31.0
Requires-Dist: python-dotenv >=1.0.1
